{"stat.useItem.276":28,"stat.useItem.23":1,"stat.walkOneCm":319843,"stat.leaveGame":10,"stat.killEntity.Slime":2,"stat.killEntity.LavaSlime":1,"stat.useItem.162":51,"stat.jump":658,"stat.swimOneCm":4448,"stat.useItem.126":3,"stat.fallOneCm":32662,"achievement.exploreAllBiomes":{"value":0,"progress":["Savanna Plateau","moon","asteroids","marsFlat","Plains","Savanna"]},"achievement.openInventory":187,"stat.damageTaken":-2147470883,"stat.mobKills":22,"stat.useItem.383":69,"stat.flyOneCm":546860,"stat.deaths":4,"stat.drop":101,"stat.playOneMinute":139278,"stat.useItem.5":10,"stat.useItem.3":1,"stat.damageDealt":3165,"stat.diveOneCm":398}